pcba_helper/__init__.py
pcba_helper/cli.py
pcba_helper/common.py
pcba_helper/templates/auth.php.template
pcba_helper/templates/base.template
pcba_helper/templates/index.template
pcba_helper/templates/overview.template
pcba_helper/templates/php/login.php
pcba_helper/templates/php/logout.php
pcba_helper/templates/static/overview.css
pcba_helper/templates/static/style.css
pcba_helper/version.py
pcba_helper-0.2.0.dist-info/LICENSE.txt
pcba_helper-0.2.0.dist-info/METADATA
pcba_helper-0.2.0.dist-info/WHEEL
pcba_helper-0.2.0.dist-info/entry_points.txt
pcba_helper-0.2.0.dist-info/RECORD
