Metadata-Version: 2.3
Name: pcba_helper
Version: 0.2.0
Summary: Create deployment folder for KiCAD based PCBA
Home-page: https://github.com/brainelectronics/pcba_helper
License: MIT
Author: brainelectronics
Author-email: info@brainelectronics.de
Requires-Python: >=3.9,<4.0
Classifier: Development Status :: 5 - Production/Stable
Classifier: Intended Audience :: Developers
Classifier: License :: OSI Approved :: MIT License
Classifier: Programming Language :: Python :: 3
Classifier: Programming Language :: Python :: 3.9
Classifier: Programming Language :: Python :: 3.10
Classifier: Programming Language :: Python :: 3.11
Classifier: Programming Language :: Python :: 3.12
Classifier: Programming Language :: Python :: 3.13
Classifier: Programming Language :: Python :: 3 :: Only
Classifier: Topic :: Software Development :: Build Tools
Classifier: Topic :: Software Development :: Version Control
Requires-Dist: bcrypt (>=4.2.1,<5.0.0)
Requires-Dist: jinja2 (>=3.1.5,<4.0.0)
Requires-Dist: markdown (>=3.7,<4.0)
Project-URL: Repository, https://github.com/brainelectronics/pcba_helper
